maskmoment/__init__.py
maskmoment/maskmoment.py
maskmoment/momfuncs.py
maskmoment-1.2.2.dist-info/LICENSE
maskmoment-1.2.2.dist-info/METADATA
maskmoment-1.2.2.dist-info/WHEEL
maskmoment-1.2.2.dist-info/top_level.txt
maskmoment-1.2.2.dist-info/RECORD
