Metadata-Version: 2.1
Name: maskmoment
Version: 1.2.2
Summary: Masked moments of radio data cubes
Home-page: https://github.com/tonywong94/maskmoment
Author: Tony Wong
Author-email: tonywong94@gmail.com
Classifier: Programming Language :: Python :: 3
Classifier: License :: OSI Approved :: MIT License
Classifier: Operating System :: OS Independent
License-File: LICENSE
Requires-Dist: numpy >=1.8.0
Requires-Dist: scipy
Requires-Dist: astropy
Requires-Dist: radio-beam
Requires-Dist: spectral-cube
